 [
   {
    "type": "terrain",
    "id": "t_open_air_rooved_outside_web_bridge",
	"name": "woven spider silk bridge with open air and rooved flat roof underneath",
    "description": "A complexely done bridge woven by a humanoid mutant spider.",
    "move_cost": 2,
    "symbol": "#",
	"looks_like": "fd_web",
    "color": "i_cyan",
	"roof": "t_flat_roof",
	"flags": [
      "TRANSPARENT",
	  "TRANSPARENT_FLOOR",
      "NOCOLLIDE",
	  "PERMEABLE",
	  "TRANSPARENT_FLOOR",
	  "FLAMMABLE_HARD",
	  "FLAMMABLE_ASH",
	  "FLAT",
	  "SEEN_FROM_ABOVE",
	  "THIN_OBSTACLE",
	  "BLOCK_WIND",
	  "REDUCE_SCENT"
    ],
 "bash": {
      "str_min": 40,
      "str_max": 300,
	  "bash_below": true,
      "sound": "hsh!",
      "sound_fail": "hsh!",
      "ter_set": "t_open_air_rooved_outside",
      "items": [ { "item": "rope_30", "count": [ 1, 4 ] } ]
    }
  },
  {
    "id": "t_open_air_rooved_web_bridge",
    "type": "terrain",
	"name": "woven spider silk bridge",
    "description": "A complexely done bridge woven by a humanoid mutant spider.",
    "move_cost": 2,
    "symbol": "#",
	"looks_like": "fd_web",
    "color": "i_cyan",
	"flags": [
      "TRANSPARENT",
	  "TRANSPARENT_FLOOR",
      "NOCOLLIDE",
	  "PERMEABLE",
	  "FLAMMABLE_HARD",
	  "FLAMMABLE_ASH",
	  "FLAT",
	  "INDOORS",
	  "SEEN_FROM_ABOVE",
	  "THIN_OBSTACLE",
	  "BLOCK_WIND",
	  "REDUCE_SCENT"
    ],
	 "bash": {
      "str_min": 40,
      "str_max": 300,
	  "bash_below": true,
      "sound": "hsh!",
      "sound_fail": "hsh!",
      "ter_set": "t_open_air_rooved",
      "items": [ { "item": "rope_30", "count": [ 1, 4 ] } ]
    }
  },
    {
    "type": "terrain",
    "id": "t_open_air_web_bridge",
	"name": "woven spider silk bridge",
    "description": "A complexely done bridge woven by a humanoid mutant spider.",
    "move_cost": 2,
    "symbol": "#",
	"looks_like": "fd_web",
    "color": "i_cyan",
	"flags": [
      "TRANSPARENT",
	  "TRANSPARENT_FLOOR",
      "NOCOLLIDE",
	  "PERMEABLE",
	  "FLAMMABLE_HARD",
	  "FLAMMABLE_ASH",
	  "FLAT",
	  "INDOORS",
	  "SEEN_FROM_ABOVE",
	  "THIN_OBSTACLE",
	  "BLOCK_WIND",
	  "REDUCE_SCENT"
    ],
	 "bash": {
      "str_min": 40,
      "str_max": 300,
	  "bash_below": true,
      "sound": "hsh!",
      "sound_fail": "hsh!",
      "ter_set": "t_open_air_rooved",
      "items": [ { "item": "rope_30", "count": [ 1, 4 ] } ]
    }
  },
     {
    "type": "terrain",
    "id": "t_open_air_rooved_outside_ladder_ledge",
	"name": "woven spider silk bridge with open air and rooved flat roof underneath",
    "description": "A spider web attached to a wall with webs along the wall for climbing made by a humanoid mutant spider.",
    "move_cost": 2,
    "symbol": "#",
	"looks_like": "fd_web",
    "color": "i_cyan",
	"roof": "t_flat_roof",
	"connects_to": "WALL",
	"flags": [
      "TRANSPARENT",
	  "TRANSPARENT_FLOOR",
      "NOCOLLIDE",
	  "PERMEABLE",
	  "TRANSPARENT_FLOOR",
	  "FLAMMABLE_HARD",
	  "FLAMMABLE_ASH",
	  "FLAT",
	  "Z_TRANSPARENT",
	  "LADDER",
	  "SEEN_FROM_ABOVE",
	  "THIN_OBSTACLE",
	  "BLOCK_WIND",
	  "REDUCE_SCENT"
    ],
	

 "bash": {
      "str_min": 40,
      "str_max": 300,
	  "bash_below": true,
      "sound": "hsh!",
      "sound_fail": "hsh!",
      "ter_set": "t_open_air_rooved_outside",
      "items": [ { "item": "rope_30", "count": [ 1, 4 ] } ]
    }
  },
  {
    "id": "t_open_air_rooved_web_ladder_ledge",
    "type": "terrain",
	"name": "woven spider silk bridge",
    "description": "A spider web attached to a wall with webs along the wall for climbing made by a humanoid mutant spider.",
    "move_cost": 2,
    "symbol": "#",
	"connects_to": "WALL",
	"looks_like": "fd_web",
    "color": "i_cyan",
	
	"flags": [
      "TRANSPARENT",
	  "TRANSPARENT_FLOOR",
      "NOCOLLIDE",
	  "PERMEABLE",
	  "FLAMMABLE_HARD",
	  "FLAMMABLE_ASH",
	  "Z_TRANSPARENT",
	  "FLAT",
	  "LADDER",
	  "INDOORS",
	  "SEEN_FROM_ABOVE",
	  "THIN_OBSTACLE",
	  "BLOCK_WIND",
	  "REDUCE_SCENT"
    ],
	 "bash": {
      "str_min": 40,
      "str_max": 300,
	  "bash_below": true,
      "sound": "hsh!",
      "sound_fail": "hsh!",
      "ter_set": "t_open_air_rooved",
      "items": [ { "item": "rope_30", "count": [ 1, 4 ] } ]
    }
  },
    {
    "type": "terrain",
    "id": "t_open_air_web_ladder_ledge",
	"name": "woven spider silk bridge",
    "description": "A spider web attached to a wall with webs along the wall for climbing made by a humanoid mutant spider.",
    "move_cost": 2,
    "symbol": "#",
	"looks_like": "fd_web",
    "color": "i_cyan",
    "connects_to": "WALL",
	"flags": [
      "TRANSPARENT",
	  "TRANSPARENT_FLOOR",
      "NOCOLLIDE",
	  "PERMEABLE",
	  "FLAMMABLE_HARD",
	  "FLAMMABLE_ASH",
	  "FLAT",
	  "Z_TRANSPARENT",
	  "INDOORS",
	  "SEEN_FROM_ABOVE",
	  "THIN_OBSTACLE",
	  "BLOCK_WIND",
	  "REDUCE_SCENT"
    ],
	 "bash": {
      "str_min": 40,
      "str_max": 300,
	  "bash_below": true,
      "sound": "hsh!",
      "sound_fail": "hsh!",
      "ter_set": "t_open_air_rooved",
      "items": [ { "item": "rope_30", "count": [ 1, 4 ] } ]
    }
  },
  {
    "type": "terrain",
    "id": "t_treetop_web_web_bridge",
	"name": "woven spider silk bridge with tree top underneath",
    "description": "A complexely done bridge woven by a humanoid mutant spider. Beware surface is unstable, tree top is underneath.",
    "move_cost": 2,
    "symbol": "#",
	"looks_like": "fd_web",
    "color": [ "light_green", "green", "yellow_yellow", "brown" ],
	"flags": [
      "TRANSPARENT",
	  "TRANSPARENT_FLOOR",
      "NOCOLLIDE",
	  "PERMEABLE",
	  "FLAMMABLE",
	  "FLAMMABLE_ASH",
	  "FLAT",
	  "UNSTABLE",
	  "SEEN_FROM_ABOVE",
	  "THIN_OBSTACLE",
	  "BLOCK_WIND",
	  "CLIMBABLE",
	  "SINGLE_SUPPORT",
	  "REDUCE_SCENT"
    ],

 "bash": {
      "str_min": 40,
      "str_max": 300,
	  "bash_below": true,
      "sound": "hsh!",
      "sound_fail": "hsh!",
      "ter_set": "t_treetop",
      "items": [ { "item": "rope_30", "count": [ 1, 4 ] } ]
    }
  },
  {
    "type": "terrain",
    "id": "t_treetop_evergreen_web_bridge",
	"name": "woven spider silk bridge with evergreen tree top underneath",
    "description": "A complexely done bridge woven by a humanoid mutant spider. Beware surface is unstable, evergreen tree top is underneath.",
    "move_cost": 2,
    "symbol": "#",
	"looks_like": "fd_web",
    "color": [ "green" ],
	"flags": [
      "TRANSPARENT",
	  "TRANSPARENT_FLOOR",
      "NOCOLLIDE",
	  "PERMEABLE",
	  "FLAMMABLE",
	  "FLAMMABLE_ASH",
	  "FLAT",
	  "UNSTABLE",
	  "SEEN_FROM_ABOVE",
	  "THIN_OBSTACLE",
	  "BLOCK_WIND",
	  "CLIMBABLE",
	  "SINGLE_SUPPORT",
	  "REDUCE_SCENT"
    ],

 "bash": {
      "str_min": 40,
      "str_max": 300,
	  "bash_below": true,
      "sound": "hsh!",
      "sound_fail": "hsh!",
      "ter_set": "t_treetop_evergreen",
      "items": [ { "item": "rope_30", "count": [ 1, 4 ] } ]
    }
  },
  {
    "type": "terrain",
    "id": "t_treetop_dead_web_bridge",
	"name": "woven spider silk bridge with dead tree top underneath",
    "description": "A complexely done bridge woven by a humanoid mutant spider. Beware surface is unstable, dead tree top is underneath.",
    "move_cost": 2,
    "symbol": "#",
	"looks_like": "fd_web",
    "color": "brown",
	"flags": [
      "TRANSPARENT",
	  "TRANSPARENT_FLOOR",
      "NOCOLLIDE",
	  "PERMEABLE",
	  "FLAMMABLE",
	  "FLAMMABLE_ASH",
	  "FLAT",
	  "UNSTABLE",
	  "SEEN_FROM_ABOVE",
	  "THIN_OBSTACLE",
	  "BLOCK_WIND",
	  "CLIMBABLE",
	  "SINGLE_SUPPORT",
	  "REDUCE_SCENT"
    ],

 "bash": {
      "str_min": 40,
      "str_max": 300,
	  "bash_below": true,
      "sound": "hsh!",
      "sound_fail": "hsh!",
      "ter_set": "t_open_air_rooved_outside",
      "items": [ { "item": "rope_30", "count": [ 1, 4 ] } ]
    }
  },
  {
    "type": "terrain",
    "id": "t_treetop_giant_fern_web_bridge",
	"name": "woven spider silk bridge with giant fern top underneath",
    "description": "A complexely done bridge woven by a humanoid mutant spider. Beware surface is unstable, giant fern is underneath.",
    "move_cost": 2,
    "symbol": "#",
	"looks_like": "fd_web",
    "color": "red",
	"flags": [
      "TRANSPARENT",
	  "TRANSPARENT_FLOOR",
      "NOCOLLIDE",
	  "PERMEABLE",
	  "FLAMMABLE",
	  "FLAMMABLE_ASH",
	  "FLAT",
	  "UNSTABLE",
	  "SEEN_FROM_ABOVE",
	  "THIN_OBSTACLE",
	  "BLOCK_WIND",
	  "CLIMBABLE",
	  "SINGLE_SUPPORT",
	  "REDUCE_SCENT"
    ],

 "bash": {
      "str_min": 40,
      "str_max": 300,
	  "bash_below": true,
      "sound": "hsh!",
      "sound_fail": "hsh!",
      "ter_set": "t_treetop_evergreen",
      "items": [ { "item": "rope_30", "count": [ 1, 4 ] } ]
    }
  }
]